drug_nme/.DS_Store
drug_nme/__init__.py
drug_nme/fetch.py
drug_nme/plot.py
drug_nme/scrape.py
drug_nme/target.py
drug_nme/utils.py
drug_nme-0.1.4.dist-info/METADATA
drug_nme-0.1.4.dist-info/WHEEL
drug_nme-0.1.4.dist-info/licenses/LICENSE
drug_nme-0.1.4.dist-info/RECORD
