Metadata-Version: 2.4
Name: drug-nme
Version: 0.1.4
Summary: Get Drug Approvals
License: MIT
License-File: LICENSE
Author: Tony Eight Lin
Author-email: tonyelin@tmu.edu.tw
Requires-Python: >=3.10
Classifier: License :: OSI Approved :: MIT License
Classifier: Programming Language :: Python :: 3
Classifier: Programming Language :: Python :: 3.10
Classifier: Programming Language :: Python :: 3.11
Classifier: Programming Language :: Python :: 3.12
Classifier: Programming Language :: Python :: 3.13
Classifier: Programming Language :: Python :: 3.14
Requires-Dist: JPype1
Requires-Dist: beautifulsoup4 (<=4.12.3)
Requires-Dist: hypothesis
Requires-Dist: legendkit (<=0.3.4)
Requires-Dist: matplotlib (<=3.10.1)
Requires-Dist: pandas (>=1.5.0)
Requires-Dist: pytest
Requires-Dist: requests
Requires-Dist: seaborn (<=0.13.2)
Requires-Dist: tabula-py (<=2.9.3)
Requires-Dist: tqdm (>=4.66.4,<5.0.0)
Project-URL: Repository, https://github.com/tlint101/drug_nme.git
